kailab/__init__.py
kailab/core.py
kailab-0.3.0.dist-info/METADATA
kailab-0.3.0.dist-info/WHEEL
kailab-0.3.0.dist-info/top_level.txt
kailab-0.3.0.dist-info/RECORD
